LICENSE
MANIFEST.in
README.rst
setup.py
wsgi_graphql.py
wsgi_graphql.egg-info/PKG-INFO
wsgi_graphql.egg-info/SOURCES.txt
wsgi_graphql.egg-info/dependency_links.txt
wsgi_graphql.egg-info/requires.txt
wsgi_graphql.egg-info/top_level.txt