Metadata-Version: 1.1
Name: wsgi-graphql
Version: 0.0.2
Summary: Create a WSGI Application for a GraphQL schema.
Home-page: https://github.com/moritzmhmk/wsgi-graphql
Author: Moritz K.
Author-email: moritzmhmk@googlemail.com
License: MIT
Download-URL: https://github.com/moritzmhmk/wsgi-graphql/archive/v0.0.2.tar.gz
Keywords: graphql,wsgi,api,rest
Platform: UNKNOWN
